{
  "demo": true,
  "locations": {
    "start": {
      "type": "circle",
      "center": {
        "latitude": 47.400222,
        "longitude": 8.440767
      },
      "radius": 10
    },
    "A": {
      "type": "circle",
      "center": {
        "latitude": 47.400217,
        "longitude": 8.440767
      },
      "radius": 5
    }
  },
  "screens": {
    "start": {
      "type": "choices",
      "text": "## Pick a screen type",
      "choices": [{
        "text": "Navigation with arrow and distance",
        "next": "nav-defaults"
      }, {
        "text": "Navigation with color",
        "next": "nav-color"
      }, {
        "text": "Text",
        "next": "1"
      }, {
        "text": "Input",
        "next": "2"
      }, {
        "text": "Multiple Choice",
        "next": "3"
      }, {
        "text": "Finish",
        "next": "finish"
      }]
    },
    "nav-defaults": {
      "type": "navigate",
      "location": "A",
      "next": "start"
    },
    "nav-color": {
      "type": "navigate",
      "location": "A",
      "options": {
        "colorSteps": 3,
        "compass": false,
        "distance": false
      },
      "next": "start"
    },
    "1": {
      "type": "text",
      "text": "## Simple Text Screen\n\nTell a part of the story or describe the current location.\n\nFree text, written in [markdown](https://help.github.com/articles/markdown-basics/).",
      "next": "start"
    },
    "2": {
      "type": "input",
      "text": "## Input Screen\n\nAsk a question, and only the correct answer will let the player continue.\n\n_1 + 2?_",
      "answer": "3",
      "next": "start"
    },
    "3": {
      "type": "choices",
      "text": "## Multiple choice\n\nNavigation to the next screen is blocked until the user selects an option. Different options can cause navigation to happen to different next screens or increase the players score points.",
      "choices": [{
        "text": "Options can use the __markdown__ format any other text"
      }, {
        "text": "Options can have a 'points' property by which the players score is increased"
      }, {
        "text": "Options can have a 'next' property pointing to the next screen"
      }, {
        "text": "It's also possible to have a default 'next' property on the choices definition. Specifying 'next' on an option takes precedence over the default."
      }],
      "next": "start"
    },
    "finish": {
      "type": "finish"
    }
  }
}
